setup.cfg
setup.py
admitad/__init__.py
admitad/api.py
admitad/client.py
admitad/constants.py
admitad/exceptions.py
admitad/transport.py
admitad.egg-info/PKG-INFO
admitad.egg-info/SOURCES.txt
admitad.egg-info/dependency_links.txt
admitad.egg-info/requires.txt
admitad.egg-info/top_level.txt